reesaurora/__init__.py
reesaurora/auxillary_rees.py
reesaurora/plots.py
reesaurora-1.0.3.dist-info/DESCRIPTION.rst
reesaurora-1.0.3.dist-info/METADATA
reesaurora-1.0.3.dist-info/RECORD
reesaurora-1.0.3.dist-info/WHEEL
reesaurora-1.0.3.dist-info/metadata.json
reesaurora-1.0.3.dist-info/top_level.txt
