Metadata-Version: 2.0
Name: reesaurora
Version: 1.0.3
Summary: Model of Earth ionosphere.
Home-page: https://github.com/scivision/reesaurora
Author: Michael Hirsch, Ph.D
Author-email: UNKNOWN
License: UNKNOWN
Platform: UNKNOWN
Classifier: Development Status :: 4 - Beta
Classifier: Environment :: Console
Classifier: Intended Audience :: Science/Research
Classifier: License :: OSI Approved :: GNU Affero General Public License v3 or later (AGPLv3+)
Classifier: Operating System :: OS Independent
Classifier: Programming Language :: Python :: 3.6
Classifier: Topic :: Scientific/Engineering :: Atmospheric Science
Requires-Python: >=3.6
Requires-Dist: gridaurora
Requires-Dist: msise00
Requires-Dist: numpy
Requires-Dist: python-dateutil
Requires-Dist: pytz
Requires-Dist: scipy
Requires-Dist: xarray
Provides-Extra: plot
Requires-Dist: matplotlib; extra == 'plot'
Requires-Dist: seaborn; extra == 'plot'
Provides-Extra: tests
Requires-Dist: coveralls; extra == 'tests'
Requires-Dist: nose; extra == 'tests'
Requires-Dist: pytest; extra == 'tests'
